dispel/__init__.py
dispel/_version.py
dispel/docutils.py
dispel/utils.py
dispel/data/__init__.py
dispel/data/collections.py
dispel/data/core.py
dispel/data/devices.py
dispel/data/epochs.py
dispel/data/flags.py
dispel/data/levels.py
dispel/data/measures.py
dispel/data/raw.py
dispel/data/validators.py
dispel/data/values.py
dispel/io/__init__.py
dispel/io/core.py
dispel/io/export.py
dispel/io/flags.py
dispel/io/raw.py
dispel/io/utils.py
dispel/processing/__init__.py
dispel/processing/assertions.py
dispel/processing/core.py
dispel/processing/data_set.py
dispel/processing/data_trace.py
dispel/processing/epochs.py
dispel/processing/extract.py
dispel/processing/flags.py
dispel/processing/level.py
dispel/processing/level_filters.py
dispel/processing/modalities.py
dispel/processing/trace.py
dispel/processing/transform.py
dispel/processing/utils.py
dispel/providers/__init__.py
dispel/providers/registry.py
dispel/providers/ads/__init__.py
dispel/providers/ads/data.py
dispel/providers/ads/io.py
dispel/providers/ads/tasks/__init__.py
dispel/providers/ads/tasks/gait.py
dispel/providers/ads/tasks/grip.py
dispel/providers/ads/tasks/passive.py
dispel/providers/ads/tasks/sbt_utt.py
dispel/providers/apdm/__init__.py
dispel/providers/apdm/data.py
dispel/providers/apdm/io.py
dispel/providers/apdm/tasks/__init__.py
dispel/providers/apdm/tasks/gait.py
dispel/providers/bdh/__init__.py
dispel/providers/bdh/data.py
dispel/providers/bdh/transform.py
dispel/providers/bdh/io/__init__.py
dispel/providers/bdh/io/core.py
dispel/providers/bdh/io/cps.py
dispel/providers/bdh/io/drawing.py
dispel/providers/bdh/io/gait.py
dispel/providers/bdh/io/msis29.py
dispel/providers/bdh/io/neuroqol.py
dispel/providers/bdh/io/pinch.py
dispel/providers/bdh/io/sbt_utt.py
dispel/providers/bdh/io/survey.py
dispel/providers/bdh/io/voice.py
dispel/providers/bdh/tasks/__init__.py
dispel/providers/bdh/tasks/alsfrs.py
dispel/providers/bdh/tasks/ft.py
dispel/providers/bdh/tasks/gait.py
dispel-0.0.3.dist-info/LICENSE
dispel-0.0.3.dist-info/METADATA
dispel-0.0.3.dist-info/WHEEL
dispel-0.0.3.dist-info/top_level.txt
dispel-0.0.3.dist-info/RECORD
