Metadata-Version: 2.1
Name: dispel
Version: 0.0.3
Summary: A python DIgital Signal ProcEssing Library developed to standardize extraction of sensor-derived measures (SDMs) from wearables or smartphones data.
Author: Alf Scotland and Gautier Cosne and Adrien Juraver and Angelos Karatsidis and Joaquin Penalver de Andres
Classifier: Development Status :: 2 - Pre-Alpha
Classifier: Intended Audience :: Developers
Classifier: Natural Language :: English
Classifier: Programming Language :: Python :: 3
Classifier: Programming Language :: Python :: 3.8
Classifier: Programming Language :: Python :: 3.9
Requires-Python: >=3.8
License-File: LICENSE
Requires-Dist: networkx
Requires-Dist: pandas ==1.3.5
Requires-Dist: numpy
Requires-Dist: scipy
Requires-Dist: scikit-learn
Requires-Dist: fastdtw
Requires-Dist: gatspy
Requires-Dist: ground >=2.0.5
Requires-Dist: bentley-ottmann >=1.0.0
Requires-Dist: deprecated
Requires-Dist: packaging
Requires-Dist: jellyfish
Requires-Dist: PyWavelets
Requires-Dist: multimethod ==1.5
Requires-Dist: soundfile
Requires-Dist: unidecode ==1.2.0
Requires-Dist: numpy-quaternion ==2022.4.3
Requires-Dist: h5py
Requires-Dist: wrapt ==1.14.0
Provides-Extra: dev
Requires-Dist: coverage ; extra == 'dev'
Requires-Dist: ruff ; extra == 'dev'
Requires-Dist: black ; extra == 'dev'
Requires-Dist: isort ; extra == 'dev'
Requires-Dist: doc8 ; extra == 'dev'
Requires-Dist: mypy ; extra == 'dev'
Requires-Dist: types-docutils ; extra == 'dev'
Requires-Dist: types-Jinja2 ; extra == 'dev'
Requires-Dist: types-Deprecated ; extra == 'dev'
Requires-Dist: pre-commit ; extra == 'dev'
Requires-Dist: pytest ; extra == 'dev'
Requires-Dist: pytest-cov ; extra == 'dev'
Requires-Dist: pytest-doctestplus ; extra == 'dev'
Requires-Dist: pytest-profiling ; extra == 'dev'
Requires-Dist: pytest-runner ; extra == 'dev'
Requires-Dist: pytest-sphinx ; extra == 'dev'
Requires-Dist: pytest-sugar ; extra == 'dev'
Requires-Dist: pytest-icdiff ; extra == 'dev'
Requires-Dist: pytest-deadfixtures ; extra == 'dev'
Requires-Dist: pytest-xdist ; extra == 'dev'
Requires-Dist: watchdog ; extra == 'dev'
Provides-Extra: docs
Requires-Dist: docutils ; extra == 'docs'
Requires-Dist: sphinx ; extra == 'docs'
Requires-Dist: urllib3 <2 ; extra == 'docs'
Requires-Dist: jinja2 ; extra == 'docs'
Requires-Dist: numpydoc ; extra == 'docs'
Requires-Dist: pydata-sphinx-theme ; extra == 'docs'
Requires-Dist: sphinxcontrib-mermaid ; extra == 'docs'
Requires-Dist: sphinx-mdinclude ; extra == 'docs'
Requires-Dist: sphinx-plotly-directive ; extra == 'docs'
